online_conformal/__init__.py
online_conformal/base.py
online_conformal/dataset.py
online_conformal/enbpi.py
online_conformal/faci.py
online_conformal/model_sigma.py
online_conformal/nex_conformal.py
online_conformal/ogd.py
online_conformal/saocp.py
online_conformal/split_conformal.py
online_conformal/utils.py
online_conformal/visualize.py
online_conformal-1.0.2.dist-info/LICENSE
online_conformal-1.0.2.dist-info/METADATA
online_conformal-1.0.2.dist-info/WHEEL
online_conformal-1.0.2.dist-info/top_level.txt
online_conformal-1.0.2.dist-info/RECORD
