Metadata-Version: 2.1
Name: online-conformal
Version: 1.0.2
Summary: A library for time series conformal prediction
Home-page: https://github.com/salesforce/online_conformal
Author: Aadyot Bhatnagar
Author-email: abhatnagar@salesforce.com
License: Apache 2.0
License-File: LICENSE
Requires-Dist: datasets
Requires-Dist: jinja2 (>=3.0)
Requires-Dist: matplotlib
Requires-Dist: numpy
Requires-Dist: pandas
Requires-Dist: salesforce-merlion
Requires-Dist: scipy
Requires-Dist: tqdm
